caduceussocket/__init__.py
caduceussocket/connection.py
caduceussocket/session.py
caduceussocket/status.py
caduceussocket/template.py
caduceussocket-0.1.5.dist-info/entry_points.txt
caduceussocket-0.1.5.dist-info/WHEEL
caduceussocket-0.1.5.dist-info/METADATA
caduceussocket-0.1.5.dist-info/RECORD
