Metadata-Version: 2.1
Name: caduceussocket
Version: 0.1.5
Summary: A python socket manager.
Home-page: https://github.com/C-Bookie/Caduceus
License: MIT
Keywords: sosket
Author: Callum Burns-Curd
Author-email: callum@fish.cat
Requires-Python: >=3.7,<4.0
Classifier: License :: OSI Approved :: MIT License
Classifier: Programming Language :: Python :: 3
Classifier: Programming Language :: Python :: 3.7
Classifier: Programming Language :: Python :: 3.8
Project-URL: Repository, https://github.com/C-Bookie/Caduceus
